portfolio/__init__.py
portfolio/portfolio_report.py
tests/__init__.py
tests/conftest.py
tests/test_io.py
tests/test_portfolio_report.py
portfolio_report_Sealeon-1.0.4.dist-info/LICENSE
portfolio_report_Sealeon-1.0.4.dist-info/METADATA
portfolio_report_Sealeon-1.0.4.dist-info/WHEEL
portfolio_report_Sealeon-1.0.4.dist-info/entry_points.txt
portfolio_report_Sealeon-1.0.4.dist-info/top_level.txt
portfolio_report_Sealeon-1.0.4.dist-info/RECORD
