Metadata-Version: 2.1
Name: portfolio-report-Sealeon
Version: 1.0.4
Summary: A stock report generator
Home-page: https://github.com/sheridan-python/assignment-7-Sealeon
Author: Emily Knight
Author-email: emily.knight2@mohawkcollege.ca
License: UNKNOWN
Platform: UNKNOWN
Classifier: Programming Language :: Python :: 3
Classifier: License :: OSI Approved :: MIT License
Classifier: Operating System :: OS Independent
Classifier: Natural Language :: English
Requires-Python: >=3.6
